{
    "code": 100000,
    "data": {
        "content": [{
            "deviceType": "SM2000",
            "imageVersion": null,
            "owner": "",
            "area": {
                "id": "117c4c9f-4e09-462b-9c6e-fbb5d8be5506",
                "isDelete": 0,
                "timestamp": 1555997821000,
                "name": "北京",
                "code": "0",
                "subArea": []
            },
            "disconnectCount": 5,
            "aliasName": "",
            "img": null,
            "deviceAdditionalInfo": {
                "id": "2d94e601-57ab-418e-ab4b-af4966b9fd7c",
                "isDelete": 0,
                "timestamp": 1556513812000,
                "frameName": null,
                "frameUseLabel": null,
                "location": null,
                "owner": "ss",
                "aliasName": "192.168.2.33",
                "frameAliasLabel": null,
                "deviceFlag": "SM2000"
            },
            "isDelete": 0,
            "ip": "192.168.2.33",
            "description": null,
            "Vendor": "ss",
            "nodeGroup": null,
            "deviceStatus": 0,
            "protocol": null,
            "shelfList": [{
                "id": "060fa0e6-69d1-4c50-b64f-d00ec58695f0",
                "isDelete": 0,
                "timestamp": 1556513812000,
                "shelfIndex": 4,
                "type": "ExpShelf",
                "nameCn": "扩展机框4",
                "status": 0,
                "slotList": null
            }, {
                "id": "29c604ff-70b4-4f1e-a6af-6b5093f48ff0",
                "isDelete": 0,
                "timestamp": 1556513812000,
                "shelfIndex": 0,
                "type": "MainShelf",
                "nameCn": "主机框",
                "status": 0,
                "slotList": null
            }, {
                "id": "7cf4e487-edbd-4648-ac8b-daef3e1a35d0",
                "isDelete": 0,
                "timestamp": 1556513812000,
                "shelfIndex": 3,
                "type": "ExpShelf",
                "nameCn": "扩展机框3",
                "status": 0,
                "slotList": null
            }, {
                "id": "86efaa41-21fd-4bbc-a75f-d34984df8a03",
                "isDelete": 0,
                "timestamp": 1556513812000,
                "shelfIndex": 2,
                "type": "ExpShelf",
                "nameCn": "扩展机框2",
                "status": 0,
                "slotList": null
            }, {
                "id": "bca64ddc-5b97-402a-9ae8-5e1c809dcafa",
                "isDelete": 0,
                "timestamp": 1556513812000,
                "shelfIndex": 1,
                "type": "ExpShelf",
                "nameCn": "扩展机框1",
                "status": 0,
                "slotList": null
            }],
            "port": 0,
            "name": "白广路SM2000_LPR",
            "location": "",
            "id": "c95dc96d-7da7-4e93-a831-3b9a3476f624",
            "NEType": "LPR",
            "deviceLocation": null,
            "timestamp": 1556513812000
        }, {
            "deviceType": "SM2000",
            "imageVersion": null,
            "owner": "",
            "area": {
                "id": "117c4c9f-4e09-462b-9c6e-fbb5d8be5506",
                "isDelete": 0,
                "timestamp": 1555997821000,
                "name": "北京",
                "code": "0",
                "subArea": []
            },
            "disconnectCount": 5,
            "aliasName": "",
            "img": null,
            "deviceAdditionalInfo": {
                "id": "45821175-06a1-40ea-ad07-261c5fabf532",
                "isDelete": 0,
                "timestamp": 1556514189000,
                "frameName": null,
                "frameUseLabel": null,
                "location": null,
                "owner": "ss",
                "aliasName": "192.168.1.133",
                "frameAliasLabel": null,
                "deviceFlag": "SM2000"
            },
            "isDelete": 0,
            "ip": "192.168.1.133",
            "description": null,
            "Vendor": "ss",
            "nodeGroup": null,
            "deviceStatus": 0,
            "protocol": null,
            "shelfList": [{
                "id": "00fc81dd-5a6a-430b-b0cb-8d58fac9c47c",
                "isDelete": 0,
                "timestamp": 1556514190000,
                "shelfIndex": 3,
                "type": "ExpShelf",
                "nameCn": "扩展机框3",
                "status": 0,
                "slotList": null
            }, {
                "id": "0d8d8a6b-dc20-422f-9240-447270173e9b",
                "isDelete": 0,
                "timestamp": 1556514190000,
                "shelfIndex": 4,
                "type": "ExpShelf",
                "nameCn": "扩展机框4",
                "status": 0,
                "slotList": null
            }, {
                "id": "13ea5947-908f-4c21-9297-f8f13fbf115f",
                "isDelete": 0,
                "timestamp": 1556514189000,
                "shelfIndex": 1,
                "type": "ExpShelf",
                "nameCn": "扩展机框1",
                "status": 0,
                "slotList": null
            }, {
                "id": "239d4318-7390-42e6-b930-1e6d808062ac",
                "isDelete": 0,
                "timestamp": 1556514189000,
                "shelfIndex": 0,
                "type": "MainShelf",
                "nameCn": "主机框",
                "status": 0,
                "slotList": null
            }, {
                "id": "fdcbb2e0-ab42-4aa0-83ee-68a77a464255",
                "isDelete": 0,
                "timestamp": 1556514190000,
                "shelfIndex": 2,
                "type": "ExpShelf",
                "nameCn": "扩展机框2",
                "status": 0,
                "slotList": null
            }],
            "port": 0,
            "name": "白广路SM2000_LPR_kk",
            "location": "",
            "id": "cebd2a6c-2802-4f2b-b536-b9f178fa8a66",
            "NEType": "LPR",
            "deviceLocation": null,
            "timestamp": 1556514189000
        }],
        "last": true,
        "totalElements": 2,
        "totalPages": 1,
        "sort": null,
        "numberOfElements": 2,
        "first": true,
        "size": 200,
        "number": 0
    }
}